{
  "transcript_id": "p002_hypertension_followup",
  "scenario": "41-year-old female teacher returning for a hypertension follow-up. Openly admits inconsistent adherence to lisinopril 20 mg (~4/7 days), bothered by ACE-inhibitor cough, mildly worried about lightheadedness on standing. Has two young kids, father had MI at 62 (lifelong smoker), wants to avoid more medications if possible.",
  "patient_utterances": [
    "I'm here for my blood pressure check, but I want to be straight with you — I haven't been good about taking the pills. Some weeks I just forget, and honestly when I feel fine I don't see the point. Plus the lisinopril gives me this dry cough that drives me crazy at night.",
    "I take it maybe four days out of seven if I'm being generous. Mornings are the worst — I'm getting ready, the kids are losing it, and it just slips. The cough started maybe two months in and hasn't gone away. I've also had a little dizziness when I stand up fast — not bad, just a moment.",
    "No chest pain. No vision changes — that I'd be more worried about. I get those dizzy moments standing up but nothing where I almost fell or anything. No leg swelling. No real headaches. And no — definitely no thoughts of hurting myself or anything like that. I'm frustrated, not depressed.",
    "Just the lisinopril 20 mg in the morning when I take it. No other prescriptions. No allergies. My mom was on blood pressure pills for years and did okay, my dad had a heart attack at 62 but he smoked his whole life. I don't smoke. I'm trying to walk more — got an Apple Watch and it nags me, which is kind of working.",
    "Honestly? I want fewer pills, not more. If there's a way to get my numbers down without the cough, I'd take that. But I also don't want to do something stupid that ends with me in a hospital bed — I have two kids in elementary school. I need to be around."
  ],
  "intake_trace": [
    {
      "turn": 1,
      "agent_prompt": "What brings you in today? Take your time and tell me what's been going on.",
      "patient_utterance": "I'm here for my blood pressure check, but I want to be straight with you — I haven't been good about taking the pills. Some weeks I just forget, and honestly when I feel fine I don't see the point. Plus the lisinopril gives me this dry cough that drives me crazy at night.",
      "profile_after": {
        "problems": [
          {
            "label": "high blood pressure",
            "onset": null,
            "severity": null,
            "timing": null,
            "associated_symptoms": [],
            "interventions_tried": [
              "lisinopril"
            ],
            "status": "unknown"
          }
        ],
        "medications": [
          "lisinopril (unknown dose, frequency)"
        ],
        "allergies": [],
        "relevant_history": [],
        "patient_goals": [
          "manage blood pressure"
        ],
        "emotional_cues": [
          {
            "cue": "frustration",
            "evidence_quote": "I haven't been good about taking the pills. Some weeks I just forget, and honestly when I feel fine I don't see the point."
          },
          {
            "cue": "frustration",
            "evidence_quote": "the lisinopril gives me this dry cough that drives me crazy at night"
          }
        ],
        "red_flags": [],
        "unknowns": [
          "problems[0].onset",
          "problems[0].severity",
          "problems[0].timing",
          "red_flag_screen_complete",
          "allergies",
          "medications",
          "relevant_history"
        ],
        "turn_count": 1,
        "completion_status": "in_progress"
      },
      "complete": false
    },
    {
      "turn": 2,
      "agent_prompt": "Before we go further, I want to check on a few quick safety questions. Have you had any chest pain, trouble breathing, sudden weakness or numbness, severe headaches, unexplained bleeding, or any thoughts of harming yourself recently?",
      "patient_utterance": "I take it maybe four days out of seven if I'm being generous. Mornings are the worst — I'm getting ready, the kids are losing it, and it just slips. The cough started maybe two months in and hasn't gone away. I've also had a little dizziness when I stand up fast — not bad, just a moment.",
      "profile_after": {
        "problems": [
          {
            "label": "high blood pressure",
            "onset": null,
            "severity": null,
            "timing": "about four days a week",
            "associated_symptoms": [
              "dry cough",
              "dizziness upon standing"
            ],
            "interventions_tried": [
              "lisinopril"
            ],
            "status": "unknown"
          }
        ],
        "medications": [
          "lisinopril (unknown dose, frequency)"
        ],
        "allergies": [],
        "relevant_history": [],
        "patient_goals": [
          "manage blood pressure"
        ],
        "emotional_cues": [
          {
            "cue": "frustration",
            "evidence_quote": "I take it maybe four days out of seven if I'm being generous. Mornings are the worst — I'm getting ready, the kids are losing it, and it just slips."
          },
          {
            "cue": "frustration",
            "evidence_quote": "the lisinopril gives me this dry cough that drives me crazy at night"
          }
        ],
        "red_flags": [],
        "unknowns": [
          "problems[0].onset",
          "problems[0].severity",
          "red_flag_screen_complete",
          "allergies",
          "medications",
          "relevant_history"
        ],
        "turn_count": 2,
        "completion_status": "in_progress"
      },
      "complete": false
    },
    {
      "turn": 3,
      "agent_prompt": "Before we go further, I want to check on a few quick safety questions. Have you had any chest pain, trouble breathing, sudden weakness or numbness, severe headaches, unexplained bleeding, or any thoughts of harming yourself recently?",
      "patient_utterance": "No chest pain. No vision changes — that I'd be more worried about. I get those dizzy moments standing up but nothing where I almost fell or anything. No leg swelling. No real headaches. And no — definitely no thoughts of hurting myself or anything like that. I'm frustrated, not depressed.",
      "profile_after": {
        "problems": [
          {
            "label": "high blood pressure",
            "onset": null,
            "severity": null,
            "timing": "about four days a week",
            "associated_symptoms": [
              "dry cough",
              "dizziness upon standing"
            ],
            "interventions_tried": [
              "lisinopril"
            ],
            "status": "unknown"
          }
        ],
        "medications": [
          "lisinopril (unknown dose, frequency)"
        ],
        "allergies": [],
        "relevant_history": [],
        "patient_goals": [
          "manage blood pressure"
        ],
        "emotional_cues": [
          {
            "cue": "frustration",
            "evidence_quote": "I take it maybe four days out of seven if I'm being generous. Mornings are the worst — I'm getting ready, the kids are losing it, and it just slips."
          },
          {
            "cue": "frustration",
            "evidence_quote": "the lisinopril gives me this dry cough that drives me crazy at night"
          },
          {
            "cue": "frustration",
            "evidence_quote": "I'm frustrated, not depressed"
          }
        ],
        "red_flags": [],
        "unknowns": [
          "problems[0].onset",
          "problems[0].severity",
          "red_flag_screen_complete",
          "allergies",
          "medications",
          "relevant_history"
        ],
        "turn_count": 3,
        "completion_status": "in_progress"
      },
      "complete": false
    },
    {
      "turn": 4,
      "agent_prompt": "When did the high blood pressure first start?",
      "patient_utterance": "Just the lisinopril 20 mg in the morning when I take it. No other prescriptions. No allergies. My mom was on blood pressure pills for years and did okay, my dad had a heart attack at 62 but he smoked his whole life. I don't smoke. I'm trying to walk more — got an Apple Watch and it nags me, which is kind of working.",
      "profile_after": {
        "problems": [
          {
            "label": "high blood pressure",
            "onset": null,
            "severity": null,
            "timing": "about four days a week",
            "associated_symptoms": [
              "dry cough",
              "dizziness upon standing"
            ],
            "interventions_tried": [
              "lisinopril"
            ],
            "status": "unknown"
          }
        ],
        "medications": [
          "lisinopril (20 mg, daily)"
        ],
        "allergies": [
          "No known allergies"
        ],
        "relevant_history": [
          "Family history: mother on blood pressure pills, father had heart attack at 62 (smoker)",
          "Lifestyle: non-smoker, trying to increase physical activity with Apple Watch"
        ],
        "patient_goals": [
          "manage blood pressure",
          "increase physical activity"
        ],
        "emotional_cues": [
          {
            "cue": "frustration",
            "evidence_quote": "I take it maybe four days out of seven if I'm being generous. Mornings are the worst — I'm getting ready, the kids are losing it, and it just slips."
          },
          {
            "cue": "frustration",
            "evidence_quote": "the lisinopril gives me this dry cough that drives me crazy at night"
          },
          {
            "cue": "frustration",
            "evidence_quote": "I'm frustrated, not depressed"
          }
        ],
        "red_flags": [],
        "unknowns": [
          "problems[0].onset",
          "problems[0].severity",
          "red_flag_screen_complete"
        ],
        "turn_count": 4,
        "completion_status": "in_progress"
      },
      "complete": false
    },
    {
      "turn": 5,
      "agent_prompt": "When did the high blood pressure first start?",
      "patient_utterance": "Honestly? I want fewer pills, not more. If there's a way to get my numbers down without the cough, I'd take that. But I also don't want to do something stupid that ends with me in a hospital bed — I have two kids in elementary school. I need to be around.",
      "profile_after": {
        "problems": [
          {
            "label": "high blood pressure",
            "onset": null,
            "severity": null,
            "timing": "about four days a week",
            "associated_symptoms": [
              "dry cough",
              "dizziness upon standing"
            ],
            "interventions_tried": [
              "lisinopril"
            ],
            "status": "unknown"
          }
        ],
        "medications": [
          "lisinopril (20 mg, daily)"
        ],
        "allergies": [
          "No known allergies"
        ],
        "relevant_history": [
          "Family history: mother on blood pressure pills, father had heart attack at 62 (smoker)",
          "Lifestyle: non-smoker, trying to increase physical activity with Apple Watch"
        ],
        "patient_goals": [
          "manage blood pressure",
          "increase physical activity",
          "fewer medications",
          "avoid hospitalization"
        ],
        "emotional_cues": [
          {
            "cue": "frustration",
            "evidence_quote": "I take it maybe four days out of seven if I'm being generous. Mornings are the worst — I'm getting ready, the kids are losing it, and it just slips."
          },
          {
            "cue": "frustration",
            "evidence_quote": "the lisinopril gives me this dry cough that drives me crazy at night"
          },
          {
            "cue": "frustration",
            "evidence_quote": "I'm frustrated, not depressed"
          },
          {
            "cue": "worry",
            "evidence_quote": "I don't want to do something stupid that ends with me in a hospital bed — I have two kids in elementary school. I need to be around."
          }
        ],
        "red_flags": [],
        "unknowns": [
          "problems[0].onset",
          "problems[0].severity",
          "red_flag_screen_complete"
        ],
        "turn_count": 5,
        "completion_status": "in_progress"
      },
      "complete": false
    }
  ],
  "profile": {
    "problems": [
      {
        "label": "high blood pressure",
        "onset": null,
        "severity": null,
        "timing": "about four days a week",
        "associated_symptoms": [
          "dry cough",
          "dizziness upon standing"
        ],
        "interventions_tried": [
          "lisinopril"
        ],
        "status": "unknown"
      }
    ],
    "medications": [
      "lisinopril (20 mg, daily)"
    ],
    "allergies": [
      "No known allergies"
    ],
    "relevant_history": [
      "Family history: mother on blood pressure pills, father had heart attack at 62 (smoker)",
      "Lifestyle: non-smoker, trying to increase physical activity with Apple Watch"
    ],
    "patient_goals": [
      "manage blood pressure",
      "increase physical activity",
      "fewer medications",
      "avoid hospitalization"
    ],
    "emotional_cues": [
      {
        "cue": "frustration",
        "evidence_quote": "I take it maybe four days out of seven if I'm being generous. Mornings are the worst — I'm getting ready, the kids are losing it, and it just slips."
      },
      {
        "cue": "frustration",
        "evidence_quote": "the lisinopril gives me this dry cough that drives me crazy at night"
      },
      {
        "cue": "frustration",
        "evidence_quote": "I'm frustrated, not depressed"
      },
      {
        "cue": "worry",
        "evidence_quote": "I don't want to do something stupid that ends with me in a hospital bed — I have two kids in elementary school. I need to be around."
      }
    ],
    "red_flags": [],
    "unknowns": [
      "problems[0].onset",
      "problems[0].severity",
      "red_flag_screen_complete"
    ],
    "turn_count": 5,
    "completion_status": "in_progress"
  },
  "ranked_docs": {
    "sub_queries": [
      {
        "source": "problem",
        "source_index": 0,
        "addresses": "problems[0]",
        "text": "Adult primary care: high blood pressure | timing about four days a week | associated with dry cough, dizziness upon standing | tried lisinopril. What guideline-based assessment, workup, or management is recommended?"
      },
      {
        "source": "goal",
        "source_index": 0,
        "addresses": "patient_goals[0]",
        "text": "Patient goal: \"manage blood pressure\". What clinician communication, shared decision-making, or counseling guidance addresses this goal?"
      },
      {
        "source": "goal",
        "source_index": 1,
        "addresses": "patient_goals[1]",
        "text": "Patient goal: \"increase physical activity\". What clinician communication, shared decision-making, or counseling guidance addresses this goal?"
      },
      {
        "source": "goal",
        "source_index": 2,
        "addresses": "patient_goals[2]",
        "text": "Patient goal: \"fewer medications\". What clinician communication, shared decision-making, or counseling guidance addresses this goal?"
      },
      {
        "source": "goal",
        "source_index": 3,
        "addresses": "patient_goals[3]",
        "text": "Patient goal: \"avoid hospitalization\". What clinician communication, shared decision-making, or counseling guidance addresses this goal?"
      },
      {
        "source": "global_context",
        "source_index": 0,
        "addresses": null,
        "text": "Patient context — medications: lisinopril (20 mg, daily) | allergies: No known allergies | history: Family history: mother on blood pressure pills, father had heart attack at 62 (smoker); Lifestyle: non-smoker, trying to increase physical activity with Apple Watch"
      }
    ],
    "documents": [
      {
        "pmid": "40577011",
        "title": "Interventions to Address Potentially Inappropriate Prescribing for Older Primary Care Patients: A Systematic Review and Meta-Analysis.",
        "journal": "JAMA network open",
        "pub_year": 2025,
        "pub_date": "2025-06-02",
        "pub_types": [
          "Journal Article",
          "Systematic Review",
          "Meta-Analysis",
          "Research Support, Non-U.S. Gov't"
        ],
        "issuing_body": null,
        "chunks": [
          {
            "chunk_id": "40577011_006",
            "pmid": "40577011",
            "section_label": "RESULTS",
            "text": "Of the 14 649 records identified, 118 randomized clinical trials (comprising 417 412 patients) were included in this review. Interventions to address potentially inappropriate prescribing were associated with a reduction in the number of medications prescribed (SMD, -0.25 [95% CI, -0.38 to -0.13]), equivalent to approximately 0.5 fewer medications per patient. However, there were no substantial differences in the other outcomes, including nonserious adverse drug reactions (RR, 0.92 [95% CI, 0.58-1.46]), injurious falls (SMD, 0.01 [95% CI, -0.12 to 0.14]), quality of life (SMD, 0.09 [95% CI, -0.04 to 0.23]), medical visits (SMD, 0.02 [95% CI, -0.02 to 0.07]), emergency department admissions (RR, 1.02 [95% CI, 0.96-1.08]), hospitalizations (RR, 0.95 [95% CI, 0.89-1.02]), or all-cause mortality (RR, 0.94 [95% CI, 0.85-1.04]).",
            "semantic_similarity": 0.7035372257232666,
            "matched_sub_query_indices": [
              3
            ]
          }
        ],
        "full_text": "IMPORTANCE: Prescriptions for potentially inappropriate medications are common and, by definition, may carry risks that outweigh benefits.\n\nOBJECTIVE: To determine whether interventions to address potentially inappropriate prescribing for older primary care patients are associated with changes in the number of medications prescribed, drug-related harms, hospitalizations, and mortality.\n\nDATA SOURCES: MEDLINE, Embase, and the Cochrane Central Register of Controlled Trials were searched from inception to September 6, 2024.\n\nSTUDY SELECTION: Randomized clinical trials of interventions to address potentially inappropriate prescribing for older primary care patients (aged ≥65 years) residing in the community or in long-term care facilities, such as nursing homes or assisted-living facilities, were included.\n\nDATA EXTRACTION AND SYNTHESIS: Two researchers independently screened the records and abstracted data using the Preferred Reporting Items for Systematic Reviews and Meta-Analyses (PRISMA) reporting guideline. Data were pooled using random-effects models.\n\nMAIN OUTCOMES AND MEASURES: The planned outcomes were the number of medications, nonserious adverse drug reactions, injurious falls, quality of life, medical visits, emergency department visits, hospitalizations, and all-cause mortality. Random-effects meta-analyses were performed using the inverse variance method for similar studies, reporting risk ratios (RRs) or standardized mean differences (SMDs). Heterogeneity was assessed with I2 values, and publication bias was assessed with funnel plots and the Egger regression test.\n\nRESULTS: Of the 14 649 records identified, 118 randomized clinical trials (comprising 417 412 patients) were included in this review. Interventions to address potentially inappropriate prescribing were associated with a reduction in the number of medications prescribed (SMD, -0.25 [95% CI, -0.38 to -0.13]), equivalent to approximately 0.5 fewer medications per patient. However, there were no substantial differences in the other outcomes, including nonserious adverse drug reactions (RR, 0.92 [95% CI, 0.58-1.46]), injurious falls (SMD, 0.01 [95% CI, -0.12 to 0.14]), quality of life (SMD, 0.09 [95% CI, -0.04 to 0.23]), medical visits (SMD, 0.02 [95% CI, -0.02 to 0.07]), emergency department admissions (RR, 1.02 [95% CI, 0.96-1.08]), hospitalizations (RR, 0.95 [95% CI, 0.89-1.02]), or all-cause mortality (RR, 0.94 [95% CI, 0.85-1.04]).\n\nCONCLUSIONS AND RELEVANCE: In this systematic review and meta-analysis, interventions to address potentially inappropriate prescribing were associated with reductions in the number of medications prescribed, with no substantial change in other outcomes. These findings suggest that inappropriate prescribing interventions may be implemented to safely reduce the number of medications prescribed to older adults in the primary care setting. Future studies should continue to evaluate these interventions using standardized criteria and consistently report potential harms to support data synthesis and capture key outcomes such as quality of life, hospitalization, and mortality.",
        "addresses_concerns": [
          "sub_query[3]"
        ],
        "semantic_similarity": 0.7035372257232666,
        "recency_score": 0.875,
        "authority_score": 0.82,
        "coverage_bonus": 0.16666666666666666,
        "total_score": 0.7074352795283001
      },
      {
        "pmid": "38533994",
        "title": "Mobile phone text messaging for medication adherence in secondary prevention of cardiovascular disease.",
        "journal": "The Cochrane database of systematic reviews",
        "pub_year": 2024,
        "pub_date": "2024-03-27",
        "pub_types": [
          "Journal Article",
          "Systematic Review",
          "Meta-Analysis"
        ],
        "issuing_body": null,
        "chunks": [
          {
            "chunk_id": "38533994_004",
            "pmid": "38533994",
            "section_label": "DATA COLLECTION AND ANALYSIS",
            "text": "We used standard Cochrane methods. Our primary outcomes were medication adherence, fatal cardiovascular events, non-fatal cardiovascular events, and combined CVD event. Secondary outcomes were low-density lipoprotein cholesterol for the effect of statins, blood pressure for antihypertensive drugs, heart rate for the effect of beta-blockers, urinary 11-dehydrothromboxane B2 for the antiplatelet effects of aspirin, adverse effects, and patient-reported experience. We used GRADE to assess the certainty of the evidence for each outcome.",
            "semantic_similarity": 0.6654831171035767,
            "matched_sub_query_indices": [
              5
            ]
          }
        ],
        "full_text": "BACKGROUND: Cardiovascular diseases (CVDs) are the leading cause of death globally, accounting for almost 18 million deaths annually. People with CVDs have a five times greater chance of suffering a recurrent cardiovascular event than people without known CVDs. Although drug interventions have been shown to be cost-effective in reducing the risk of recurrent cardiovascular events, adherence to medication remains suboptimal. As a scalable and cost-effective approach, mobile phone text messaging presents an opportunity to convey health information, deliver electronic reminders, and encourage behaviour change. However, it is uncertain whether text messaging can improve medication adherence and clinical outcomes. This is an update of a Cochrane review published in 2017.\n\nOBJECTIVES: To evaluate the benefits and harms of mobile phone text messaging for improving medication adherence in people with CVDs compared to usual care.\n\nSEARCH METHODS: We searched CENTRAL, MEDLINE, Embase, four other databases, and two trial registers. We also checked the reference lists of all primary included studies and relevant systematic reviews and meta-analyses. The date of the latest search was 30 August 2023.\n\nSELECTION CRITERIA: We included randomised controlled trials (RCTs) with participants with established arterial occlusive events. We included trials investigating interventions using short message service (SMS) or multimedia messaging service (MMS) with the aim of improving adherence to medication for the secondary prevention of cardiovascular events. The comparator was usual care. We excluded cluster-RCTs and quasi-RCTs.\n\nDATA COLLECTION AND ANALYSIS: We used standard Cochrane methods. Our primary outcomes were medication adherence, fatal cardiovascular events, non-fatal cardiovascular events, and combined CVD event. Secondary outcomes were low-density lipoprotein cholesterol for the effect of statins, blood pressure for antihypertensive drugs, heart rate for the effect of beta-blockers, urinary 11-dehydrothromboxane B2 for the antiplatelet effects of aspirin, adverse effects, and patient-reported experience. We used GRADE to assess the certainty of the evidence for each outcome.\n\nMAIN RESULTS: We included 18 RCTs involving a total of 8136 participants with CVDs. We identified 11 new studies in the review update and seven studies in the previous version of the review. Participants had various CVDs including acute coronary syndrome, coronary heart disease, stroke, myocardial infarction, and angina. All studies were conducted in middle- and high-income countries, with no studies conducted in low-income countries. The mean age of participants was 53 to 64 years. Participants were recruited from hospitals or cardiac rehabilitation facilities. Follow-up ranged from one to 12 months. There was variation in the characteristics of text messages amongst studies (e.g. delivery method, frequency, theoretical grounding, content used, personalisation, and directionality). The content of text messages varied across studies, but generally included medication reminders and healthy lifestyle information such as diet, physical activity, and weight loss. Text messages offered advice, motivation, social support, and health education to promote behaviour changes and regular medication-taking. We assessed risk of bias for all studies as high, as all studies had at least one domain at unclear or high risk of bias. Medication adherence Due to different evaluation score systems and inconsistent definitions applied for the measurement of medication adherence, we did not conduct meta-analysis for medication adherence. Ten out of 18 studies showed a beneficial effect of mobile phone text messaging for medication adherence compared to usual care, whereas the other eight studies showed either a reduction or no difference in medication adherence with text messaging compared to usual care. Overall, the evidence is very uncertain about the effects of mobile phone text messaging for medication adherence when compared to usual care. Fatal cardiovascular events Text messaging may have little to no effect on fatal cardiovascular events compared to usual care (odds ratio 0.83, 95% confidence interval (CI) 0.47 to 1.45; 4 studies, 1654 participants; low-certainty evidence). Non-fatal cardiovascular events We found very low-certainty evidence that text messaging may have little to no effect on non-fatal cardiovascular events. Two studies reported non-fatal cardiovascular events, neither of which found evidence of a difference between groups. Combined CVD events We found very low-certainty evidence that text messaging may have little to no effect on combined CVD events. Only one study reported combined CVD events, and did not find evidence of a difference between groups. Low-density lipoprotein cholesterol Text messaging may have little to no effect on low-density lipoprotein cholesterol compared to usual care (mean difference (MD) -1.79 mg/dL, 95% CI -4.71 to 1.12; 8 studies, 4983 participants; very low-certainty evidence). Blood pressure Text messaging may have little to no effect on systolic blood pressure (MD -0.93 mmHg, 95% CI -3.55 to 1.69; 8 studies, 5173 participants; very low-certainty evidence) and diastolic blood pressure (MD -1.00 mmHg, 95% CI -2.49 to 0.50; 5 studies, 3137 participants; very low-certainty evidence) when compared to usual care. Heart rate Text messaging may have little to no effect on heart rate compared to usual care (MD -0.46 beats per minute, 95% CI -1.74 to 0.82; 4 studies, 2946 participants; very low-certainty evidence).\n\nAUTHORS' CONCLUSIONS: Due to limited evidence, we are uncertain if text messaging reduces medication adherence, fatal and non-fatal cardiovascular events, and combined cardiovascular events in people with cardiovascular diseases when compared to usual care. Furthermore, text messaging may result in little or no effect on low-density lipoprotein cholesterol, blood pressure, and heart rate compared to usual care. The included studies were of low methodological quality, and no studies assessed the effects of text messaging in low-income countries or beyond the 12-month follow-up. Long-term and high-quality randomised trials are needed, particularly in low-income countries.",
        "addresses_concerns": [
          "sub_query[5]"
        ],
        "semantic_similarity": 0.6654831171035767,
        "recency_score": 0.75,
        "authority_score": 0.98,
        "coverage_bonus": 0.16666666666666666,
        "total_score": 0.6954082252184551
      },
      {
        "pmid": "38604640",
        "title": "Do patients with type 2 diabetes mellitus included in randomised clinical trials differ from general-practice patients? A cross-sectional comparative study.",
        "journal": "BMJ open",
        "pub_year": 2024,
        "pub_date": "2024-04-11",
        "pub_types": [
          "Journal Article",
          "Comparative Study",
          "Systematic Review"
        ],
        "issuing_body": null,
        "chunks": [
          {
            "chunk_id": "38604640_005",
            "pmid": "38604640",
            "section_label": "RESULTS",
            "text": "General-practice patients were older than randomised controlled trial patients (mean (SD) 68.8 (1.1) vs 59.9 years (standardised difference 0.8)) and had a higher body mass index (mean (SD) 31.5 (6.9) vs 28.2 kg/m2 (standardised difference 0.5)) but smoked less (11.0% vs 29.3% (standardised difference -0.6)). They more frequently used antihypertensive drugs (82.1% vs 37.5% (standardised difference 1.2)) but less frequently had a myocardial infarction (7.6% vs 23.1% (standardised difference -1.1)).",
            "semantic_similarity": 0.6506648659706116,
            "matched_sub_query_indices": [
              0,
              5
            ]
          }
        ],
        "full_text": "OBJECTIVES: To compare the characteristics of patients with type 2 diabetes mellitus in general practice and those included in randomised controlled trials on which clinical practice guidelines are based.\n\nDESIGN: Cross-sectional comparative study.\n\nSETTING: We asked 45 general practitioners from three French Departments to identify the 15 patients with type 2 diabetes mellitus they most recently saw in consultation. In parallel, we selected randomised controlled trials included in the Cochrane systematic review on which the clinical practice guidelines for type 2 diabetes mellitus were based.\n\nPARTICIPANTS: We included 675 patients with type 2 diabetes mellitus, and data were collected from 23 randomised controlled trials, corresponding to 36 059 patients.\n\nOUTCOME MEASURES: Characteristics of general-practice patients were extracted from medical records by a unique observer. The same baseline characteristics of patients included in randomised controlled trials from the Cochrane systematic review were extracted and meta-analysed. We assessed standardised differences between these two series of baseline characteristics. A difference greater than 0.10 in absolute value was considered meaningful.\n\nRESULTS: General-practice patients were older than randomised controlled trial patients (mean (SD) 68.8 (1.1) vs 59.9 years (standardised difference 0.8)) and had a higher body mass index (mean (SD) 31.5 (6.9) vs 28.2 kg/m2 (standardised difference 0.5)) but smoked less (11.0% vs 29.3% (standardised difference -0.6)). They more frequently used antihypertensive drugs (82.1% vs 37.5% (standardised difference 1.2)) but less frequently had a myocardial infarction (7.6% vs 23.1% (standardised difference -1.1)).\n\nCONCLUSIONS: Patients with type 2 diabetes mellitus cared for in general practice differ in a number of important aspects from patients included in randomised controlled trials on which clinical practice guidelines are based. This situation hampers the applicability of these guidelines. Future randomised trials should include patients who better fit the 'average' general-practice patient with type 2 diabetes mellitus to help improve the translation of study findings in daily practice.",
        "addresses_concerns": [
          "sub_query[0]",
          "sub_query[5]"
        ],
        "semantic_similarity": 0.6506648659706116,
        "recency_score": 0.75,
        "authority_score": 0.8,
        "coverage_bonus": 0.16666666666666666,
        "total_score": 0.6519990996519726
      },
      {
        "pmid": "33658141",
        "title": "Communicating with older adults with long-term conditions about self-management goals: A systematic review and thematic synthesis.",
        "journal": "Patient education and counseling",
        "pub_year": 2021,
        "pub_date": "2021-10",
        "pub_types": [
          "Journal Article",
          "Research Support, Non-U.S. Gov't",
          "Systematic Review"
        ],
        "issuing_body": null,
        "chunks": [
          {
            "chunk_id": "33658141_004",
            "pmid": "33658141",
            "section_label": "PRACTICE IMPLICATIONS",
            "text": "We encourage HCPs to prepare older adults to engage actively with SDM and the goal setting process by employing patient-centred communication resources. These could assist with identifying different types of goals that are realistic and relevant to patients in daily life.",
            "semantic_similarity": 0.7130434513092041,
            "matched_sub_query_indices": [
              1,
              2,
              3,
              4
            ]
          }
        ],
        "full_text": "OBJECTIVE: To synthesise a body of fine-grained observational research on communication between healthcare professionals (HCPs), older adults, and carers regarding self-management goals and actions.\n\nMETHODS: We conducted a systematic review, searching nine electronic databases and the grey literature. Two reviewers independently selected for inclusion following a two-stage process and studies and discrepancies were resolved through consultation with the review team.\n\nRESULTS: 898 records were retrieved, and eight studies were included in the review. Aggregative thematic analysis resulted in 13 categories of communication practices across three decision-making domains: (1) initiating: actions occurring prior to the commitment point; (2) proposing: putting forward a course of action; and (3) committing and closing: committing (or not) to the course of action.\n\nCONCLUSIONS: Despite an increasing emphasis on the importance of personalised care planning and shared decision-making (SDM) to support older people's health and wellbeing, HCPs did not consistently practice this approach and, in some cases, worked in opposition to it.\n\nPRACTICE IMPLICATIONS: We encourage HCPs to prepare older adults to engage actively with SDM and the goal setting process by employing patient-centred communication resources. These could assist with identifying different types of goals that are realistic and relevant to patients in daily life.",
        "addresses_concerns": [
          "sub_query[1]",
          "sub_query[2]",
          "sub_query[3]",
          "sub_query[4]"
        ],
        "semantic_similarity": 0.7130434513092041,
        "recency_score": 0.375,
        "authority_score": 0.8,
        "coverage_bonus": 0.5,
        "total_score": 0.6415217256546022
      },
      {
        "pmid": "33464342",
        "title": "Interventions for Tobacco Cessation in Adults, Including Pregnant Persons: Updated Evidence Report and Systematic Review for the US Preventive Services Task Force.",
        "journal": "JAMA",
        "pub_year": 2021,
        "pub_date": "2021-01-19",
        "pub_types": [
          "Journal Article",
          "Research Support, U.S. Gov't, P.H.S.",
          "Systematic Review"
        ],
        "issuing_body": null,
        "chunks": [
          {
            "chunk_id": "33464342_006",
            "pmid": "33464342",
            "section_label": "RESULTS",
            "text": "Sixty-seven reviews addressing pharmacotherapy and behavioral interventions were included as well as 9 trials (N = 3942) addressing e-cigarettes for smoking cessation and 7 trials (N = 2285) of nicotine replacement therapy (NRT) use in pregnancy. Combined pharmacotherapy and behavioral interventions (pooled risk ratio [RR], 1.83 [95% CI, 1.68-1.98]), NRT (RR, 1.55 [95% CI, 1.49-1.61]), bupropion (RR, 1.64 [95% CI, 1.52-1.77]), varenicline (RR, 2.24 [95% CI, 2.06-2.43]), and behavioral interventions such as advice from clinicians (RR, 1.76 [95% CI, 1.58-1.96]) were all associated with increased quit rates compared with minimal support or placebo at 6 months or longer. None of the drugs were associated with serious adverse events. Five trials (n = 3117) reported inconsistent findings on the effectiveness of electronic cigarettes on smoking cessation at 6 to 12 months among smokers when compared with placebo or NRT, and none suggested higher rates of serious adverse events. Among pregnant persons, behavioral interventions were associated with greater smoking cessation during late pregnancy (RR, 1.35 [95% CI, 1.23-1.48]), compared with no intervention. Rates of validated cessation among pregnant women allocated to NRT compared with placebo were not significantly different (pooled RR, 1.11 [95% CI, 0.79-1.56], n = 2033).",
            "semantic_similarity": 0.6392521262168884,
            "matched_sub_query_indices": [
              5
            ]
          }
        ],
        "full_text": "IMPORTANCE: It has been estimated that in 2018 nearly 20% of adults in the US were currently using a tobacco product.\n\nOBJECTIVE: To systematically review the effectiveness and safety of pharmacotherapy, behavioral interventions, and electronic cigarettes for tobacco cessation among adults, including pregnant persons, to inform the US Preventive Services Task Force.\n\nDATA SOURCES: PubMed, PsycInfo, Database of Abstracts of Reviews of Effects, Cochrane Database of Systematic Reviews, Centre for Reviews and Dissemination of Health Technology Assessment; surveillance through September 25, 2020.\n\nSTUDY SELECTION: Systematic reviews of tobacco cessation interventions and randomized clinical trials that evaluated the effects of electronic cigarettes (e-cigarettes) or pharmacotherapy among pregnant persons.\n\nDATA EXTRACTION AND SYNTHESIS: Independent critical appraisal and data abstraction; qualitative synthesis and random-effects meta-analyses.\n\nMAIN OUTCOMES AND MEASURES: Health outcomes, tobacco cessation at 6 months or more, and adverse events.\n\nRESULTS: Sixty-seven reviews addressing pharmacotherapy and behavioral interventions were included as well as 9 trials (N = 3942) addressing e-cigarettes for smoking cessation and 7 trials (N = 2285) of nicotine replacement therapy (NRT) use in pregnancy. Combined pharmacotherapy and behavioral interventions (pooled risk ratio [RR], 1.83 [95% CI, 1.68-1.98]), NRT (RR, 1.55 [95% CI, 1.49-1.61]), bupropion (RR, 1.64 [95% CI, 1.52-1.77]), varenicline (RR, 2.24 [95% CI, 2.06-2.43]), and behavioral interventions such as advice from clinicians (RR, 1.76 [95% CI, 1.58-1.96]) were all associated with increased quit rates compared with minimal support or placebo at 6 months or longer. None of the drugs were associated with serious adverse events. Five trials (n = 3117) reported inconsistent findings on the effectiveness of electronic cigarettes on smoking cessation at 6 to 12 months among smokers when compared with placebo or NRT, and none suggested higher rates of serious adverse events. Among pregnant persons, behavioral interventions were associated with greater smoking cessation during late pregnancy (RR, 1.35 [95% CI, 1.23-1.48]), compared with no intervention. Rates of validated cessation among pregnant women allocated to NRT compared with placebo were not significantly different (pooled RR, 1.11 [95% CI, 0.79-1.56], n = 2033).\n\nCONCLUSIONS AND RELEVANCE: There is strong evidence that a range of pharmacologic and behavioral interventions, both individually and in combination, are effective in increasing smoking cessation in nonpregnant adults. In pregnancy, behavioral interventions are effective for smoking cessation, but data are limited on the use of pharmacotherapy for smoking cessation. Data on the effectiveness and safety of electronic cigarettes for smoking cessation among adults are also limited and results are inconsistent.",
        "addresses_concerns": [
          "sub_query[5]"
        ],
        "semantic_similarity": 0.6392521262168884,
        "recency_score": 0.375,
        "authority_score": 1.0,
        "coverage_bonus": 0.0,
        "total_score": 0.5946260631084442
      }
    ],
    "rerank_weights": {
      "semantic_similarity": 0.5,
      "recency": 0.2,
      "authority": 0.2,
      "coverage_bonus": 0.1
    },
    "top_k_chunks_per_query": 20,
    "final_n_documents": 20,
    "expansion_used": "stub"
  },
  "structured_context": {
    "clusters": [
      {
        "cluster_id": "recommendation::patient_goals::33658141_0",
        "assertion_type": "recommendation",
        "addresses_concern": "patient_goals",
        "primary_assertion": {
          "assertion_id": "33658141_0",
          "assertion_text": "Healthcare professionals should encourage older adults to engage actively with shared decision-making (SDM) and goal setting.",
          "assertion_type": "recommendation",
          "confidence": 0.9,
          "source_pmid": "33658141",
          "source_chunk_id": null,
          "addresses_concern": "patient_goals",
          "evidence_quote": "We encourage HCPs to prepare older adults to engage actively with SDM and the goal setting process"
        },
        "supporting_pmids": [
          "33658141"
        ],
        "alternative_assertions": [
          {
            "assertion_id": "33658141_1",
            "assertion_text": "Patient-centred communication resources can help identify realistic and relevant goals for older adults in daily life.",
            "assertion_type": "recommendation",
            "confidence": 0.85,
            "source_pmid": "33658141",
            "source_chunk_id": null,
            "addresses_concern": "patient_goals",
            "evidence_quote": "patient-centred communication resources...identifying different types of goals that are realistic and relevant to patients in daily life"
          }
        ],
        "convergent": false,
        "confidence": 0.9,
        "resolution_rule": "confidence",
        "resolution_rationale": "Recency: Both assertions are from the same 2021 publication, so recency does not resolve the tie. Next, authority score: both are from 'Patient education and counseling' with a score of 0.8. Moving to evidence strength, both are Journal Articles and Systematic Reviews, so no difference there. Coverage is the same as both address patient_goals. Finally, confidence is higher in the second assertion (0.85 vs 0.9), but since confidence is the last tiebreaker, the first assertion is chosen as primary based on the order of application of the rules."
      },
      {
        "cluster_id": "finding::problems[0]::38533994_0",
        "assertion_type": "finding",
        "addresses_concern": "problems[0]",
        "primary_assertion": {
          "assertion_id": "38533994_0",
          "assertion_text": "Mobile phone text messaging may have little to no effect on systolic blood pressure compared to usual care.",
          "assertion_type": "finding",
          "confidence": 0.6,
          "source_pmid": "38533994",
          "source_chunk_id": null,
          "addresses_concern": "problems[0]",
          "evidence_quote": "text messaging may have little to no effect on systolic blood pressure"
        },
        "supporting_pmids": [
          "38533994"
        ],
        "alternative_assertions": [
          {
            "assertion_id": "38533994_1",
            "assertion_text": "Mobile phone text messaging may have little to no effect on diastolic blood pressure compared to usual care.",
            "assertion_type": "finding",
            "confidence": 0.6,
            "source_pmid": "38533994",
            "source_chunk_id": null,
            "addresses_concern": "problems[0]",
            "evidence_quote": "text messaging may have little to no effect on diastolic blood pressure"
          },
          {
            "assertion_id": "38533994_2",
            "assertion_text": "Mobile phone text messaging may have little to no effect on low-density lipoprotein cholesterol compared to usual care.",
            "assertion_type": "finding",
            "confidence": 0.6,
            "source_pmid": "38533994",
            "source_chunk_id": null,
            "addresses_concern": "problems[0]",
            "evidence_quote": "text messaging may have little to no effect on low-density lipoprotein cholesterol"
          },
          {
            "assertion_id": "38533994_3",
            "assertion_text": "Mobile phone text messaging may have little to no effect on heart rate compared to usual care.",
            "assertion_type": "finding",
            "confidence": 0.6,
            "source_pmid": "38533994",
            "source_chunk_id": null,
            "addresses_concern": "problems[0]",
            "evidence_quote": "text messaging may have little to no effect on heart rate"
          }
        ],
        "convergent": false,
        "confidence": 0.6,
        "resolution_rule": "coverage",
        "resolution_rationale": "Recency: All assertions are from the same 2024 publication, so recency does not resolve the tie. Next, authority: all are from the Cochrane Database of Systematic Reviews with a high authority score of 0.98. Since all have the same authority, we look at evidence strength. All are Journal Articles, Systematic Reviews, and Meta-Analyses, which are the highest ranked. Finally, coverage: each assertion addresses a different aspect of problems[0], so all are retained as alternatives."
      },
      {
        "cluster_id": "finding::sub_query[3]::40577011_0",
        "assertion_type": "finding",
        "addresses_concern": "sub_query[3]",
        "primary_assertion": {
          "assertion_id": "40577011_0",
          "assertion_text": "Interventions to address potentially inappropriate prescribing were associated with a reduction in the number of medications prescribed.",
          "assertion_type": "finding",
          "confidence": 0.9,
          "source_pmid": "40577011",
          "source_chunk_id": null,
          "addresses_concern": "sub_query[3]",
          "evidence_quote": "Interventions to address potentially inappropriate prescribing were associated with a reduction in the number of medications prescribed"
        },
        "supporting_pmids": [
          "40577011"
        ],
        "alternative_assertions": [],
        "convergent": true,
        "confidence": 0.9,
        "resolution_rule": null,
        "resolution_rationale": null
      },
      {
        "cluster_id": "finding::sub_query[3]::40577011_1",
        "assertion_type": "finding",
        "addresses_concern": "sub_query[3]",
        "primary_assertion": {
          "assertion_id": "40577011_1",
          "assertion_text": "There were no substantial differences in nonserious adverse drug reactions, injurious falls, quality of life, medical visits, emergency department admissions, hospitalizations, or all-cause mortality.",
          "assertion_type": "finding",
          "confidence": 0.85,
          "source_pmid": "40577011",
          "source_chunk_id": null,
          "addresses_concern": "sub_query[3]",
          "evidence_quote": "there were no substantial differences in the other outcomes"
        },
        "supporting_pmids": [
          "40577011"
        ],
        "alternative_assertions": [],
        "convergent": true,
        "confidence": 0.85,
        "resolution_rule": null,
        "resolution_rationale": null
      },
      {
        "cluster_id": "finding::global::33464342_2",
        "assertion_type": "finding",
        "addresses_concern": null,
        "primary_assertion": {
          "assertion_id": "33464342_2",
          "assertion_text": "Among pregnant persons, behavioral interventions were associated with greater smoking cessation during late pregnancy compared with no intervention.",
          "assertion_type": "finding",
          "confidence": 0.9,
          "source_pmid": "33464342",
          "source_chunk_id": null,
          "addresses_concern": null,
          "evidence_quote": "Among pregnant persons, behavioral interventions were associated with greater smoking cessation during late pregnancy (RR, 1.35 [95% CI, 1.23-1.48]), compared with no intervention."
        },
        "supporting_pmids": [
          "33464342"
        ],
        "alternative_assertions": [],
        "convergent": true,
        "confidence": 0.9,
        "resolution_rule": null,
        "resolution_rationale": null
      },
      {
        "cluster_id": "finding::global::33464342_3",
        "assertion_type": "finding",
        "addresses_concern": null,
        "primary_assertion": {
          "assertion_id": "33464342_3",
          "assertion_text": "Rates of validated cessation among pregnant women allocated to NRT compared with placebo were not significantly different.",
          "assertion_type": "finding",
          "confidence": 0.9,
          "source_pmid": "33464342",
          "source_chunk_id": null,
          "addresses_concern": null,
          "evidence_quote": "Rates of validated cessation among pregnant women allocated to NRT compared with placebo were not significantly different (pooled RR, 1.11 [95% CI, 0.79-1.56], n = 2033)."
        },
        "supporting_pmids": [
          "33464342"
        ],
        "alternative_assertions": [],
        "convergent": true,
        "confidence": 0.9,
        "resolution_rule": null,
        "resolution_rationale": null
      },
      {
        "cluster_id": "finding::global::33464342_4",
        "assertion_type": "finding",
        "addresses_concern": null,
        "primary_assertion": {
          "assertion_id": "33464342_4",
          "assertion_text": "Data on the effectiveness and safety of electronic cigarettes for smoking cessation among adults are limited and results are inconsistent.",
          "assertion_type": "finding",
          "confidence": 0.75,
          "source_pmid": "33464342",
          "source_chunk_id": null,
          "addresses_concern": null,
          "evidence_quote": "Data on the effectiveness and safety of electronic cigarettes for smoking cessation among adults are also limited and results are inconsistent."
        },
        "supporting_pmids": [
          "33464342"
        ],
        "alternative_assertions": [],
        "convergent": true,
        "confidence": 0.75,
        "resolution_rule": null,
        "resolution_rationale": null
      },
      {
        "cluster_id": "finding::global::38604640_0",
        "assertion_type": "finding",
        "addresses_concern": null,
        "primary_assertion": {
          "assertion_id": "38604640_0",
          "assertion_text": "Patients with type 2 diabetes mellitus in general practice are older than those in randomised controlled trials.",
          "assertion_type": "finding",
          "confidence": 0.9,
          "source_pmid": "38604640",
          "source_chunk_id": null,
          "addresses_concern": null,
          "evidence_quote": "General-practice patients were older than randomised controlled trial patients (mean (SD) 68.8 (1.1) vs 59.9 years (standardised difference 0.8))"
        },
        "supporting_pmids": [
          "38604640"
        ],
        "alternative_assertions": [
          {
            "assertion_id": "38604640_1",
            "assertion_text": "General-practice patients with type 2 diabetes mellitus have a higher body mass index compared to those in randomised controlled trials.",
            "assertion_type": "finding",
            "confidence": 0.9,
            "source_pmid": "38604640",
            "source_chunk_id": null,
            "addresses_concern": null,
            "evidence_quote": "General-practice patients had a higher body mass index (mean (SD) 31.5 (6.9) vs 28.2 kg/m2 (standardised difference 0.5))"
          },
          {
            "assertion_id": "38604640_2",
            "assertion_text": "General-practice patients smoke less than those included in randomised controlled trials.",
            "assertion_type": "finding",
            "confidence": 0.9,
            "source_pmid": "38604640",
            "source_chunk_id": null,
            "addresses_concern": null,
            "evidence_quote": "General-practice patients smoked less (11.0% vs 29.3% (standardised difference -0.6))"
          },
          {
            "assertion_id": "38604640_3",
            "assertion_text": "General-practice patients more frequently use antihypertensive drugs compared to randomised controlled trial patients.",
            "assertion_type": "finding",
            "confidence": 0.9,
            "source_pmid": "38604640",
            "source_chunk_id": null,
            "addresses_concern": null,
            "evidence_quote": "General-practice patients more frequently used antihypertensive drugs (82.1% vs 37.5% (standardised difference 1.2))"
          },
          {
            "assertion_id": "38604640_4",
            "assertion_text": "General-practice patients have a lower incidence of myocardial infarction compared to randomised controlled trial patients.",
            "assertion_type": "finding",
            "confidence": 0.9,
            "source_pmid": "38604640",
            "source_chunk_id": null,
            "addresses_concern": null,
            "evidence_quote": "General-practice patients less frequently had a myocardial infarction (7.6% vs 23.1% (standardised difference -1.1))"
          },
          {
            "assertion_id": "38604640_5",
            "assertion_text": "Clinical practice guidelines for type 2 diabetes mellitus may not be as applicable to general-practice patients due to differences in patient characteristics.",
            "assertion_type": "finding",
            "confidence": 0.9,
            "source_pmid": "38604640",
            "source_chunk_id": null,
            "addresses_concern": null,
            "evidence_quote": "This situation hampers the applicability of these guidelines"
          }
        ],
        "convergent": false,
        "confidence": 0.9,
        "resolution_rule": "recency",
        "resolution_rationale": "Recency: All assertions are from the same 2024 publication; rule 1 does not resolve the tie. Next, authority score is the same for all (0.8); rule 2 does not resolve. Pub_types are identical, so rule 3 does not help. Coverage is the same as all address the same concern; rule 4 does not help. Finally, confidence is the same, so rule 5 does not apply. Since all rules are tied, any assertion can be primary, but we select the first one."
      },
      {
        "cluster_id": "finding::global::33464342_0",
        "assertion_type": "finding",
        "addresses_concern": null,
        "primary_assertion": {
          "assertion_id": "33464342_0",
          "assertion_text": "Combined pharmacotherapy and behavioral interventions are associated with increased quit rates compared with minimal support or placebo at 6 months or longer.",
          "assertion_type": "finding",
          "confidence": 0.9,
          "source_pmid": "33464342",
          "source_chunk_id": null,
          "addresses_concern": null,
          "evidence_quote": "Combined pharmacotherapy and behavioral interventions (pooled risk ratio [RR], 1.83 [95% CI, 1.68-1.98]), NRT (RR, 1.55 [95% CI, 1.49-1.61]), bupropion (RR, 1.64 [95% CI, 1.52-1.77]), varenicline (RR, 2.24 [95% CI, 2.06-2.43]), and behavioral interventions such as advice from clinicians (RR, 1.76 [95% CI, 1.58-1.96]) were all associated with increased quit rates compared with minimal support or placebo at 6 months or longer."
        },
        "supporting_pmids": [
          "33464342"
        ],
        "alternative_assertions": [
          {
            "assertion_id": "33464342_1",
            "assertion_text": "Behavioral interventions such as advice from clinicians are associated with increased quit rates compared with minimal support or placebo at 6 months or longer.",
            "assertion_type": "finding",
            "confidence": 0.9,
            "source_pmid": "33464342",
            "source_chunk_id": null,
            "addresses_concern": null,
            "evidence_quote": "behavioral interventions such as advice from clinicians (RR, 1.76 [95% CI, 1.58-1.96]) were all associated with increased quit rates compared with minimal support or placebo at 6 months or longer."
          }
        ],
        "convergent": false,
        "confidence": 0.9,
        "resolution_rule": "evidence_strength",
        "resolution_rationale": "Recency: Both assertions are from the same 2021 publication, so recency does not resolve the tie. Next, authority is considered, but both are from JAMA with the same authority score. Moving to evidence strength, the first assertion is a Systematic Review, which is higher than the second's Journal Article. Therefore, the first assertion is selected as primary."
      }
    ],
    "n_documents_processed": 5,
    "n_assertions_extracted": 19,
    "n_clusters": 9,
    "n_convergent_clusters": 5,
    "n_divergent_clusters": 4,
    "cluster_similarity_threshold": 0.75,
    "notes": [
      "Abstracts-only prototype: assertion granularity is coarser than a full-text system would produce.",
      "Module II graph expansion is stubbed in v0 (flat vector retrieval). See clinicomm.modules.m2_retrieval.expand_neighborhood."
    ]
  },
  "response": {
    "acknowledgment": "It sounds like managing your blood pressure is really challenging for you, especially with the dry cough from the lisinopril. You mentioned, \"the lisinopril gives me this dry cough that drives me crazy at night,\" and I can understand how frustrating that must be.",
    "clinical_information_per_concern": [
      {
        "concern_label": "high blood pressure",
        "profile_path": "problems[0]",
        "explanation": "High blood pressure can be tricky to manage, especially when medications cause side effects. The good news is that there are other ways to help control it, like lifestyle changes and sometimes adjusting medications.",
        "citations": [
          {
            "cluster_id": "finding::problems[0]::38533994_0",
            "primary_assertion_id": "38533994_0",
            "pmids": [
              "38533994"
            ]
          }
        ]
      },
      {
        "concern_label": "manage blood pressure",
        "profile_path": "patient_goals[0]",
        "explanation": "Setting clear goals for managing your blood pressure is a great first step. We'll work together to find strategies that fit your life and help you reach those goals.",
        "citations": [
          {
            "cluster_id": "recommendation::patient_goals::33658141_0",
            "primary_assertion_id": "33658141_0",
            "pmids": [
              "33658141"
            ]
          }
        ]
      },
      {
        "concern_label": "increase physical activity",
        "profile_path": "patient_goals[1]",
        "explanation": "Increasing physical activity is a key part of managing blood pressure. Even small steps, like using your Apple Watch to track daily activity, can make a big difference over time.",
        "citations": [
          {
            "cluster_id": "recommendation::patient_goals::33658141_0",
            "primary_assertion_id": "33658141_0",
            "pmids": [
              "33658141"
            ]
          }
        ]
      },
      {
        "concern_label": "fewer medications",
        "profile_path": "patient_goals[2]",
        "explanation": "We'll explore ways to manage your blood pressure with fewer medications, focusing on lifestyle changes and monitoring to see if adjustments can be made.",
        "citations": [
          {
            "cluster_id": "finding::sub_query[3]::40577011_0",
            "primary_assertion_id": "40577011_0",
            "pmids": [
              "40577011"
            ]
          }
        ]
      },
      {
        "concern_label": "avoid hospitalization",
        "profile_path": "patient_goals[3]",
        "explanation": "Our goal is to help you manage your blood pressure in a way that keeps you out of the hospital. This includes regular monitoring and adjusting your care plan as needed.",
        "citations": [
          {
            "cluster_id": "finding::sub_query[3]::40577011_0",
            "primary_assertion_id": "40577011_0",
            "pmids": [
              "40577011"
            ]
          }
        ]
      }
    ],
    "next_steps": [
      "We'll review your current medications and see if adjusting them could help reduce side effects.",
      "Discuss lifestyle changes that can support your blood pressure management.",
      "Set up a follow-up appointment in 2 weeks to check progress and make any necessary adjustments."
    ],
    "teach_back_prompt": "I want to make sure I explained this clearly — can you tell me, in your own words, what we're going to do next and why?",
    "follow_up_invitation": "Let's plan to meet again in 2 weeks. In the meantime, if you experience severe dizziness or your blood pressure doesn't improve, please call us right away.",
    "nurse_elements_applied": [
      "Name",
      "Understand",
      "Respect",
      "Support"
    ],
    "four_habits_elements_applied": [
      "Invest in the beginning",
      "Elicit the patient's perspective",
      "Invest in the end"
    ],
    "all_cluster_ids_used": [
      "finding::problems[0]::38533994_0",
      "recommendation::patient_goals::33658141_0",
      "finding::sub_query[3]::40577011_0"
    ],
    "all_pmids_used": [
      "38533994",
      "33658141",
      "40577011"
    ],
    "glossary_substitutions": []
  },
  "mode": "real",
  "module_timings_ms": {
    "module_1_intake": 62409.2969968915,
    "module_2_retrieval": 57.48159438371658,
    "module_3_reasoning": 50341.3303270936,
    "module_4_response": 39506.89487159252,
    "total_ms": 152315.00378996134
  }
}